<?xml version="1.0" encoding="UTF-8"?>
<configuration>
    <include resource="org/springframework/boot/logging/logback/defaults.xml"/>
    <include resource="org/springframework/boot/logging/logback/console-appender.xml"/>

    <springProperty scope="context" name="appName" source="spring.application.name"/>

    <!-- 1. Console Appender (JSON format for Prod, Color for Dev) -->
    <appender name="CONSOLE_JSON" class="ch.qos.logback.core.ConsoleAppender">
        <encoder class="net.logstash.logback.encoder.LogstashEncoder">
            <timeZone>UTC</timeZone>
        </encoder>
    </appender>

    <!-- 2. Logstash TCP Appender -->
    <appender name="LOGSTASH" class="net.logstash.logback.appender.LogstashTcpSocketAppender">
        <destination>localhost:5000</destination>
        <encoder class="net.logstash.logback.encoder.LogstashEncoder">
            <customFields>{"app_name":"${appName}"}</customFields>
        </encoder>
        <!-- Drop logs if Logstash is down to prevent blocking app -->
        <connectionStrategy>
            <roundRobin>
                <connectionTTL>5 minutes</connectionTTL>
            </roundRobin>
        </connectionStrategy>
    </appender>

    <!-- 3. Rolling File Appender -->
    <appender name="FILE" class="ch.qos.logback.core.rolling.RollingFileAppender">
        <rollingPolicy class="ch.qos.logback.core.rolling.TimeBasedRollingPolicy">
            <!-- daily rollover -->
            <fileNamePattern>logs/ticketmaster.%d{yyyy-MM-dd}.log</fileNamePattern>
            <!-- keep 30 days' worth of history -->
            <maxHistory>30</maxHistory>
        </rollingPolicy>
        <encoder>
            <pattern>%d{yyyy-MM-dd HH:mm:ss.SSS} [%thread] %-5level %logger{36} - %msg%n</pattern>
        </encoder>
    </appender>

    <!-- PROFILES CONFIGURATION -->

    <!-- Local/Dev: Log to Console (Color) + File -->
    <springProfile name="local,dev,default">
        <root level="INFO">
            <appender-ref ref="CONSOLE"/>
            <appender-ref ref="FILE"/>
        </root>
        <logger name="com.ds.goroute" level="DEBUG"/>
    </springProfile>

    <!-- Prod/Staging: Log to Console (JSON) + Logstash -->
    <springProfile name="prod,staging">
        <root level="INFO">
            <appender-ref ref="CONSOLE_JSON"/>
            <appender-ref ref="LOGSTASH"/>
        </root>
        <logger name="com.ds.goroute" level="INFO"/>
    </springProfile>

</configuration>
